{
    "relationships": [
        {
            "relationshipName": "employee",
            "otherEntityName": "employee",
            "relationshipType": "many-to-one",
            "otherEntityRelationshipName": "clockins",
            "otherEntityField": "id"
        }
    ],
    "fields": [
        {
            "fieldName": "sequentialRegisterNumber",
            "fieldType": "String"
        },
        {
            "fieldName": "dateTime",
            "fieldType": "ZonedDateTime"
        },
        {
            "fieldName": "registryType",
            "fieldType": "RegistryType",
            "fieldValues": "TYPE_1,TYPE_2,TYPE_3,TYPE_4,TYPE_5"
        }
    ],
    "changelogDate": "20151124151638",
    "dto": "no",
	"service": "serviceImpl",
    "entityTableName": "clockin",
    "pagination": "no"
}
